asr_types/__init__.py
asr_types/definitions.py
asr_types-1.0.1.dist-info/licenses/LICENSE
asr_types-1.0.1.dist-info/METADATA
asr_types-1.0.1.dist-info/WHEEL
asr_types-1.0.1.dist-info/top_level.txt
asr_types-1.0.1.dist-info/RECORD
