Metadata-Version: 2.4
Name: asr-types
Version: 1.0.1
Summary: Type definitions for ASR (Automatic Speech Recognition) data structures
License: MIT
Project-URL: Homepage, https://github.com/speech2srt/asr-types
Project-URL: Repository, https://github.com/speech2srt/asr-types
Project-URL: Issues, https://github.com/speech2srt/asr-types/issues
Requires-Python: >=3.10
License-File: LICENSE
Dynamic: license-file
